{
  "Quickfish": "trash",
  "Gold Ingots": "trash",
  "Drowsyness": "trash",
  "Hardfish": "trash",
  "Small Exp": "trash",
  "Compost": "trash",
  "Gold Blocks": "trash",
  "Medium Exp": "trash",
  "Semi Rare Ticket": "trash",
  "Large Compost": "trash",
  "Hidefish": "trash",
  "Diamonds": "trash",
  "Poison Oak": "trash",
  "Haste Eggs": "trash",
  "Diamond Blocks": "trash",
  "Blowfish": "trash",
  "Large Exp": "trash",
  "Crate": "trash",
  "Epic Rare Ticket": "trash",
  "Emeralds": "trash",
  "Notch Apples": "trash",
  "Emerald Blocks": "trash",
  "Zoomfish": "trash",
  "Huge Exp": "trash",
  "Copper": "trash",
  "Unrefined Mescaline x4": "trash",
  "Random Fishing Special Rare": "trash",
  "Jungle Apple": "trash",
  "Unrefined Weed x2": "trash",
  "Copper Block": "trash",
  "Hastefish": "trash",
  "Massive Exp": "trash",
  "Unrefined Mescaline x16": "trash",
  "Notch Apple Bunch": "trash",
  "Random Ultra Rare": "trash",
  "Gigantic Exp": "trash",
  "Birch Seed": "trash",
  "Crate Trio": "trash",
  "Rockfish": "trash",
  "Bait": "trash",
  "Enormous Exp": "trash",
  "Unrefined Shrooms x3": "trash",
  "Shop Crate": "trash",
  "Mining and Ultra Boost Passes": "trash",
  "Spruce Logs": "trash",
  "Overflowing Exp": "trash",
  "Arcade Token": "trash",
  "Trade Token": "trash",
  "Acacia Logs": "trash",
  "Unrefined Opiates x16": "trash",
  "Flash Fish": "trash",
  "Tumbleweed": "trash",
  "Jungle logs": "trash",
  "Flounder": "trash",
  "1x Unrefined Crack": "trash",
  "Fish Eggs": "trash",
  "Dark Oak Branch": "trash",
  "Dark Oak Logs": "trash",
  "Creature Crate": "trash",
  "Waterfall XP": "trash",
  "MYTHICAL BOOST PASS": "trash",
  "3x Spruce Cone": "trash",
  "XP Tsunami": "trash",
  "Boulderfish": "trash",
  "Bait Bunch": "trash",
  "Arcade Token x5": "trash",
  "God Apple Basket": "trash",
  "Ultra Legendary Fragment (9 Frags = 1 shard)": "trash",
  "Unrefined Shrooms x8": "trash",
  "Trade Token Bundle": "trash",
  "Creepy Crate": "trash",
  "Event Passes": "trash",
  "Event Party Passes": "trash",
  "Legendary Crumbs": "trash",
  "Enchantment Dust": "trash",
  "Mega Event Pass": "trash",
  "Ultra Legendary Shard": "trash"
} 